gpt4all_cli/__init__.py
gpt4all_cli/grammar.py
gpt4all_cli/parser.py
gpt4all_cli/revision.py
gpt4all_cli/mprov/__init__.py
gpt4all_cli/mprov/base.py
gpt4all_cli/mprov/gpt4all.py
gpt4all_cli/mprov/openai.py
gpt4all_cli-1.3.0.data/scripts/gpt4all-cli
gpt4all_cli-1.3.0.dist-info/METADATA
gpt4all_cli-1.3.0.dist-info/WHEEL
gpt4all_cli-1.3.0.dist-info/top_level.txt
gpt4all_cli-1.3.0.dist-info/RECORD
