Metadata-Version: 2.1
Name: gpt4all-cli
Version: 1.3.0
Summary: Command-line interface using GPT4ALL bindings
Home-page: https://github.com/sergei-mironov/gpt4all-cli
Author: Sergei Mironov
Author-email: sergei.v.mironov@proton.me
Classifier: Programming Language :: Python :: 3
Classifier: License :: OSI Approved :: Apache Software License
Classifier: Operating System :: POSIX :: Linux
Classifier: Topic :: Software Development :: Build Tools
Classifier: Intended Audience :: Developers
Classifier: Development Status :: 3 - Alpha
Requires-Python: >=3.6
Requires-Dist: gpt4all-bindings
Requires-Dist: gnureadline
Requires-Dist: lark
